mark2tg/__init__.py
mark2tg-0.1.dist-info/licenses/LICENSE
mark2tg-0.1.dist-info/METADATA
mark2tg-0.1.dist-info/WHEEL
mark2tg-0.1.dist-info/top_level.txt
mark2tg-0.1.dist-info/RECORD
