Metadata-Version: 2.4
Name: mark2tg
Version: 0.1
Summary: A lightweight library to convert Markdown to Telegram formatting.
Home-page: https://github.com/yourusername/mark2tg
Author: Leonid I. aka livlev && le01evf
Author-email: leonid.a.ivlev@gmail.cpom
Classifier: Programming Language :: Python :: 3
Classifier: License :: OSI Approved :: MIT License
Classifier: Operating System :: OS Independent
License-File: LICENSE
Dynamic: author
Dynamic: author-email
Dynamic: classifier
Dynamic: home-page
Dynamic: license-file
Dynamic: summary
